dsp_final/fir/rtl/fir_trans.v
`timescale 1ns / 1ps
module fir_trans(
    input wire clk,
    input wire rst_n,
    input wire signed[14:0] data_in,
    output wire signed[19:0] data_out
);
//io,parametr define
localparam inWL=15;
localparam macWL=20;
localparam tap_num = 37;
integer idx;

//store coeff
reg signed [inWL-1:0]  coeff   [0:tap_num-1];
//data * tap
//reg signed [19:0] mul    [0:36];
//acc
reg signed [macWL-1:0]  acc     [0:tap_num-2];
//dff for acc_buffer
reg signed [macWL-1:0]  dff_acc [0:tap_num-2];

reg signed [inWL*2-1:0] mul    [0:tap_num-1];
//taps宣告

initial begin
    coeff[0] = -15'd38; coeff[1] = -15'd137; coeff[2] = 15'd0;
    coeff[3] = 15'd241; coeff[4] = 15'd120; coeff[5] = -15'd331;
    coeff[6] = -15'd351; coeff[7] = 15'd338; coeff[8] = 15'd690;
    coeff[9] = -15'd178; coeff[10] = -15'd1114; coeff[11] = -15'd267;
    coeff[12] = 15'd1562; coeff[13] = 15'd1185; coeff[14] = -15'd1964;
    coeff[15] = -15'd3176; coeff[16] = 15'd2241; coeff[17] = 15'd11639;
    coeff[18] = 15'd16383; coeff[19] = 15'd11639; coeff[20] = 15'd2241;
    coeff[21] = -15'd3176; coeff[22] = -15'd1964; coeff[23] = 15'd1185;
    coeff[24] = 15'd1562; coeff[25] = -15'd267; coeff[26] = -15'd1114;
    coeff[27] = -15'd178; coeff[28] = 15'd690; coeff[29] = 15'd338;
    coeff[30] = -15'd351; coeff[31] = -15'd331; coeff[32] = 15'd120;
    coeff[33] = 15'd241; coeff[34] = 15'd0; coeff[35] = -15'd137;
    coeff[36] = -15'd38;
end

//multiply
always @* begin
    for(idx=0; idx < tap_num ; idx=idx+1)begin
       mul[idx] = data_in * coeff[idx];
    end

    for (idx=0; idx < tap_num-1 ; idx=idx+1)begin
        acc[idx] = dff_acc[idx] + mul[idx+1][29:10];
    end
end

//shift acc
always@(posedge clk or negedge rst_n)begin
    if(~rst_n)begin
        for(idx=0;idx<tap_num-1;idx=idx+1)begin
            dff_acc[idx] <= 20'd0;
        end
    end
    else begin
        dff_acc[0] <= mul[0][29:10];
        for(idx=1;idx<tap_num-1;idx=idx+1)begin
            dff_acc[idx] <= acc[idx-1];
        end
    end
end


assign data_out = acc[tap_num-2];

endmodule

dsp_final/fir/tb/fir_trans_tb.v
`timescale 1ns / 1ps
//transposed form tb

module fir_trans_tb;
    parameter inWL = 15;
    parameter macWL = 20;
    parameter Data_Num =500;

    reg signed [inWL-1:0] in;
    reg signed [inWL-1:0] tap;
    wire signed [macWL-1:0] out;
    reg clk;
    reg rst_n;

    //this is for test transposed form module
    
    fir_trans U0(
        .clk(clk),
        .rst_n(rst_n),
        .data_in(in),
        .data_out(out)
    );


    initial begin
        $dumpfile("fir.vcd");
        $dumpvars();
    end

    
    integer f_data,f_golden,error;
    reg signed [19:0] golden;
    initial begin
        clk = 1'b0;
        in = 15'd0;
        error = 0;
        golden = 20'd0;
    end

    always #5 clk = ~clk;

    initial begin
        rst_n = 1'b0;
        f_data = $fopen("/home/ubuntu/dspic_final_submit/dsp_final/data/HW_input.txt","r");
        f_golden = $fopen("/home/ubuntu/dspic_final_submit/dsp_final/data/HW_golden.txt", "r");
        #100;
        rst_n = 1'b1;
        #100; 
        repeat(500) begin
            @(posedge clk)begin
                $fscanf(f_data, "%d", in);
                $fscanf(f_golden, "%d", golden);
            end
            @(negedge clk)begin
                if(out==golden)begin
                    $display("[PASS][Pattern]%5d=%5d",golden, out);
                end
                else begin
                    $display("[ERROR][Pattern]%5d not equal to %5d",golden, out);
                end
            end
        end
        if(error == 0)
            $display("All answers match golden");
        else
            $display("None");
       
        $fclose(f_data);
        $fclose(f_golden);

        $finish;
    end

endmodule

dsp_final/fir/fir.vcd
$date
   Mon Jan  8 02:10:03 2024
$end
$version
  2022.1
$end
$timescale
  1ps
$end
$scope module fir_trans_tb $end
$var reg 15 ! in [14:0] $end
$var wire 20 " out [19:0] $end
$var reg 1 # clk $end
$var reg 1 $ rst_n $end
$var integer 32 % f_data [31:0] $end
$var integer 32 & f_golden [31:0] $end
$var integer 32 ' error [31:0] $end
$var reg 20 ( golden [19:0] $end
$scope module U0 $end
$var wire 1 ) clk $end
$var wire 1 * rst_n $end
$var wire 15 + data_in [14:0] $end
$var wire 20 " data_out [19:0] $end
$var integer 32 , idx [31:0] $end
$upscope $end
$upscope $end
$enddefinitions $end
#0
$dumpvars
b0 !
b0 "
0#
0$
b11111111111111111011000111100000 %
b11111111111111111011000111100001 &
bx '
b0 (
0)
0*
b0 +
b100100 ,
$end
#5000
1#
1)
b100100 ,
#10000
0#
0)
#15000
1#
1)
b100100 ,
#20000
0#
0)
#25000
1#
1)
b100100 ,
#30000
0#
0)
#35000
1#
1)
b100100 ,
#40000
0#
0)
#45000
1#
1)
b100100 ,
#50000
0#
0)
#55000
1#
1)
b100100 ,
#60000
0#
0)
#65000
1#
1)
b100100 ,
#70000
0#
0)
#75000
1#
1)
b100100 ,
#80000
0#
0)
#85000
1#
1)
b100100 ,
#90000
0#
0)
#95000
1#
1)
b100100 ,
#100000
0#
1$
0)
1*
#105000
1#
1)
b100100 ,
#110000
0#
0)
#115000
1#
1)
b100100 ,
#120000
0#
0)
#125000
1#
1)
b100100 ,
#130000
0#
0)
#135000
1#
1)
b100100 ,
#140000
0#
0)
#145000
1#
1)
b100100 ,
#150000
0#
0)
#155000
1#
1)
b100100 ,
#160000
0#
0)
#165000
1#
1)
b100100 ,
#170000
0#
0)
#175000
1#
1)
b100100 ,
#180000
0#
0)
#185000
1#
1)
b100100 ,
#190000
0#
0)
#195000
1#
1)
b100100 ,
#200000
0#
0)
#205000
b101100100011 !
b11111111111110010110 "
1#
b11111111111110010110 (
1)
b101100100011 +
b100100 ,
#210000
0#
0)
#215000
b11110100000010 !
b11111111110000111110 "
1#
b11111111110000111110 (
1)
b11110100000010 +
b100100 ,
#220000
0#
0)
#225000
b10000000000 !
b11111111011110110000 "
1#
b11111111011110110000 (
1)
b10000000000 +
b100100 ,
#230000
0#
0)
#235000
b100001000010011 !
b10001100001 "
1#
b10001100001 (
1)
b100001000010011 +
b100100 ,
#240000
0#
0)
#245000
b100100110111 !
b1011110011001 "
1#
b1011110011001 (
1)
b100100110111 +
b100100 ,
#250000
0#
0)
#255000
b100001111100110 !
b10101111011 "
1#
b10101111011 (
1)
b100001111100110 +
b100100 ,
#260000
0#
0)
#265000
b10101100100111 !
b11111110000011001001 "
1#
b11111110000011001001 (
1)
b10101100100111 +
b100100 ,
#270000
0#
0)
#275000
b101101010111011 !
b11111110001111111101 "
1#
b11111110001111111101 (
1)
b101101010111011 +
b100100 ,
#280000
0#
0)
#285000
b1000100010010 !
b10010110010000 "
1#
b10010110010000 (
1)
b1000100010010 +
b100100 ,
#290000
0#
0)
#295000
b1101010100 !
b11101101101101 "
1#
b11101101101101 (
1)
b1101010100 +
b100100 ,
#300000
0#
0)
#305000
b100011011101111 !
b11111110010111000000 "
1#
b11111110010111000000 (
1)
b100011011101111 +
b100100 ,
#310000
0#
0)
#315000
b11010100100101 !
b11111001111101001010 "
1#
b11111001111101001010 (
1)
b11010100100101 +
b100100 ,
#320000
0#
0)
#325000
b100111101101101 !
b11111111010010010011 "
1#
b11111111010010010011 (
1)
b100111101101101 +
b100100 ,
#330000
0#
0)
#335000
b110111010111001 !
b1001000111000000 "
1#
b1001000111000000 (
1)
b110111010111001 +
b100100 ,
#340000
0#
0)
#345000
b11010001011110 !
b101011111101011 "
1#
b101011111101011 (
1)
b11010001011110 +
b100100 ,
#350000
0#
0)
#355000
b111000101011000 !
b11110011100000111011 "
1#
b11110011100000111011 (
1)
b111000101011000 +
b100100 ,
#360000
0#
0)
#365000
b10100110110101 !
b11110000011010110000 "
1#
b11110000011010110000 (
1)
b10100110110101 +
b100100 ,
#370000
0#
0)
#375000
b111100010001011 !
b10010100110100001 "
1#
b10010100110100001 (
1)
b111100010001011 +
b100100 ,
#380000
0#
0)
#385000
b100101111110010 !
b1000001100001111111 "
1#
b1000001100001111111 (
1)
b100101111110010 +
b100100 ,
#390000
0#
0)
#395000
b111010100101 !
b1000101110101111001 "
1#
b1000101110101111001 (
1)
b111010100101 +
b100100 ,
#400000
0#
0)
#405000
b110011100011010 !
b1011101100001010 "
1#
b1011101100001010 (
1)
b110011100011010 +
b100100 ,
#410000
0#
0)
#415000
b101100111110000 !
b11000100001110100101 "
1#
b11000100001110100101 (
1)
b101100111110000 +
b100100 ,
#420000
0#
0)
#425000
b10110110111111 !
b10101111100111110110 "
1#
b10101111100111110110 (
1)
b10110110111111 +
b100100 ,
#430000
0#
0)
#435000
b11111101010111 !
b11010011100010110110 "
1#
b11010011100010110110 (
1)
b11111101010111 +
b100100 ,
#440000
0#
0)
#445000
b101100100011 !
b11111101111110111001 "
1#
b11111101111110111001 (
1)
b101100100011 +
b100100 ,
#450000
0#
0)
#455000
b101111010011110 !
b111101101010101 "
1#
b111101101010101 (
1)
b101111010011110 +
b100100 ,
#460000
0#
0)
#465000
b100000000010 !
b11111001011011111000 "
1#
b11111001011011111000 (
1)
b100000000010 +
b100100 ,
#470000
0#
0)
#475000
b10110100111001 !
b11101101000100100110 "
1#
b11101101000100100110 (
1)
b10110100111001 +
b100100 ,
#480000
0#
0)
#485000
b110100000100100 !
b11101000100010001010 "
1#
b11101000100010001010 (
1)
b110100000100100 +
b100100 ,
#490000
0#
0)
#495000
b10110110010101 !
b11100101010011110110 "
1#
b11100101010011110110 (
1)
b10110110010101 +
b100100 ,
#500000
0#
0)
#505000
b11100100110000 !
b11100111010010100001 "
1#
b11100111010010100001 (
1)
b11100100110000 +
b100100 ,
#510000
0#
0)
#515000
b11001010001101 !
b11111010000001011010 "
1#
b11111010000001011010 (
1)
b11001010001101 +
b100100 ,
#520000
0#
0)
#525000
b110110110001 !
b11001010001011001 "
1#
b11001010001011001 (
1)
b110110110001 +
b100100 ,
#530000
0#
0)
#535000
b101110101000011 !
b101110011110001000 "
1#
b101110011110001000 (
1)
b101110101000011 +
b100100 ,
#540000
0#
0)
#545000
b111100011100000 !
b100110000000111010 "
1#
b100110000000111010 (
1)
b111100011100000 +
b100100 ,
#550000
0#
0)
#555000
b111001111000 !
b11111111101110101000 "
1#
b11111111101110101000 (
1)
b111001111000 +
b100100 ,
#560000
0#
0)
#565000
b111010010000100 !
b11010000000110011001 "
1#
b11010000000110011001 (
1)
b111010010000100 +
b100100 ,
#570000
0#
0)
#575000
b110010101011111 !
b10110111000011010100 "
1#
b10110111000011010100 (
1)
b110010101011111 +
b100100 ,
#580000
0#
0)
#585000
b10100000001101 !
b11001100010000010100 "
1#
b11001100010000010100 (
1)
b10100000001101 +
b100100 ,
#590000
0#
0)
#595000
b111000001010 !
b1000001101010111 "
1#
b1000001101010111 (
1)
b111000001010 +
b100100 ,
#600000
0#
0)
#605000
b101110100010110 !
b1000010010100001111 "
1#
b1000010010100001111 (
1)
b101110100010110 +
b100100 ,
#610000
0#
0)
#615000
b100000000111111 !
b1010000111011001100 "
1#
b1010000111011001100 (
1)
b100000000111111 +
b100100 ,
#620000
0#
0)
#625000
b101000011100 !
b110000100101011110 "
1#
b110000100101011110 (
1)
b101000011100 +
b100100 ,
#630000
0#
0)
#635000
b101010000100100 !
b10101000110101 "
1#
b10101000110101 (
1)
b101010000100100 +
b100100 ,
#640000
0#
0)
#645000
b111010110001100 !
b11101111011001000111 "
1#
b11101111011001000111 (
1)
b111010110001100 +
b100100 ,
#650000
0#
0)
#655000
b111100010100001 !
b100101001010010 "
1#
b100101001010010 (
1)
b111100010100001 +
b100100 ,
#660000
0#
0)
#665000
b110111011101101 !
b110100011010011011 "
1#
b110100011010011011 (
1)
b110111011101101 +
b100100 ,
#670000
0#
0)
#675000
b10001110000010 !
b1100010000111100101 "
1#
b1100010000111100101 (
1)
b10001110000010 +
b100100 ,
#680000
0#
0)
#685000
b101000111001011 !
b1110000101111101111 "
1#
b1110000101111101111 (
1)
b101000111001011 +
b100100 ,
#690000
0#
0)
#695000
b100001000110011 !
b1010110101110011000 "
1#
b1010110101110011000 (
1)
b100001000110011 +
b100100 ,
#700000
0#
0)
#705000
b110110011001101 !
b100001111101111001 "
1#
b100001111101111001 (
1)
b110110011001101 +
b100100 ,
#710000
0#
0)
#715000
b110001111101100 !
b11101111100001011101 "
1#
b11101111100001011101 (
1)
b110001111101100 +
b100100 ,
#720000
0#
0)
#725000
b101101011010101 !
b11011000110010101010 "
1#
b11011000110010101010 (
1)
b101101011010101 +
b100100 ,
#730000
0#
0)
#735000
b101000100111101 !
b11100010010001010101 "
1#
b11100010010001010101 (
1)
b101000100111101 +
b100100 ,
#740000
0#
0)
#745000
b10100001 !
b11111110010001111011 "
1#
b11111110010001111011 (
1)
b10100001 +
b100100 ,
#750000
0#
0)
#755000
b111111100111111 !
b10110010101001000 "
1#
b10110010101001000 (
1)
b111111100111111 +
b100100 ,
#760000
0#
0)
#765000
b110101000000110 !
b10110111011111110 "
1#
b10110111011111110 (
1)
b110101000000110 +
b100100 ,
#770000
0#
0)
#775000
b10101111001010 !
b11111011111011101101 "
1#
b11111011111011101101 (
1)
b10101111001010 +
b100100 ,
#780000
0#
0)
#785000
b11000111001 !
b11010011010010101101 "
1#
b11010011010010101101 (
1)
b11000111001 +
b100100 ,
#790000
0#
0)
#795000
b110110010011001 !
b10110100110011011001 "
1#
b10110100110011011001 (
1)
b110110010011001 +
b100100 ,
#800000
0#
0)
#805000
b1100100011010 !
b10110000000100010100 "
1#
b10110000000100010100 (
1)
b1100100011010 +
b100100 ,
#810000
0#
0)
#815000
b10001100000011 !
b11000010100010001110 "
1#
b11000010100010001110 (
1)
b10001100000011 +
b100100 ,
#820000
0#
0)
#825000
b11011100001 !
b11011111111000111110 "
1#
b11011111111000111110 (
1)
b11011100001 +
b100100 ,
#830000
0#
0)
#835000
b110101100100001 !
b11111010101100001011 "
1#
b11111010101100001011 (
1)
b110101100100001 +
b100100 ,
#840000
0#
0)
#845000
b101100001100111 !
b11101010111101 "
1#
b11101010111101 (
1)
b101100001100111 +
b100100 ,
#850000
0#
0)
#855000
b110110010011011 !
b11101110111000000101 "
1#
b11101110111000000101 (
1)
b110110010011011 +
b100100 ,
#860000
0#
0)
#865000
b101111011110010 !
b11000100000100000111 "
1#
b11000100000100000111 (
1)
b101111011110010 +
b100100 ,
#870000
0#
0)
#875000
b11110001000001 !
b10100010110110110101 "
1#
b10100010110110110101 (
1)
b11110001000001 +
b100100 ,
#880000
0#
0)
#885000
b10100011111011 !
b10100001100101000011 "
1#
b10100001100101000011 (
1)
b10100011111011 +
b100100 ,
#890000
0#
0)
#895000
b111010011110000 !
b10110011100000110001 "
1#
b10110011100000110001 (
1)
b111010011110000 +
b100100 ,
#900000
0#
0)
#905000
b11110011010010 !
b10111100101110100110 "
1#
b10111100101110100110 (
1)
b11110011010010 +
b100100 ,
#910000
0#
0)
#915000
b100001111110110 !
b10111011011001100010 "
1#
b10111011011001100010 (
1)
b100001111110110 +
b100100 ,
#920000
0#
0)
#925000
b101011010001101 !
b11001011010101110101 "
1#
b11001011010101110101 (
1)
b101011010001101 +
b100100 ,
#930000
0#
0)
#935000
b100010100110000 !
b11110110001000010010 "
1#
b11110110001000010010 (
1)
b100010100110000 +
b100100 ,
#940000
0#
0)
#945000
b11011100010101 !
b11100011011000100 "
1#
b11100011011000100 (
1)
b11011100010101 +
b100100 ,
#950000
0#
0)
#955000
b110001010100110 !
b11101010010010000 "
1#
b11101010010010000 (
1)
b110001010100110 +
b100100 ,
#960000
0#
0)
#965000
b11010101010011 !
b1000000111011101 "
1#
b1000000111011101 (
1)
b11010101010011 +
b100100 ,
#970000
0#
0)
#975000
b101010001111010 !
b111100100011100 "
1#
b111100100011100 (
1)
b101010001111010 +
b100100 ,
#980000
0#
0)
#985000
b11010101001011 !
b100110001110001110 "
1#
b100110001110001110 (
1)
b11010101001011 +
b100100 ,
#990000
0#
0)
#995000
b111111111100011 !
b111010001101101101 "
1#
b111010001101101101 (
1)
b111111111100011 +
b100100 ,
#1000000
0#
0)
#1005000
b1001101011111 !
b11100001000011000 "
1#
b11100001000011000 (
1)
b1001101011111 +
b100100 ,
#1010000
0#
0)
#1015000
b100111001001100 !
b11011001000011010101 "
1#
b11011001000011010101 (
1)
b100111001001100 +
b100100 ,
#1020000
0#
0)
#1025000
b10011110001100 !
b10101000100001011011 "
1#
b10101000100001011011 (
1)
b10011110001100 +
b100100 ,
#1030000
0#
0)
#1035000
b101001111101 !
b10110011010011100000 "
1#
b10110011010011100000 (
1)
b101001111101 +
b100100 ,
#1040000
0#
0)
#1045000
b111011011011 !
b11110011001111010111 "
1#
b11110011001111010111 (
1)
b111011011011 +
b100100 ,
#1050000
0#
0)
#1055000
b111100001110011 !
b111111101011110101 "
1#
b111111101011110101 (
1)
b111100001110011 +
b100100 ,
#1060000
0#
0)
#1065000
b100111110101111 !
b1101000111011100100 "
1#
b1101000111011100100 (
1)
b100111110101111 +
b100100 ,
#1070000
0#
0)
#1075000
b110000011110 !
b1010000101101000111 "
1#
b1010000101101000111 (
1)
b110000011110 +
b100100 ,
#1080000
0#
0)
#1085000
b111001011010000 !
b10010001001 "
1#
b10010001001 (
1)
b111001011010000 +
b100100 ,
#1090000
0#
0)
#1095000
b110100100110 !
b10101110000111100110 "
1#
b10101110000111100110 (
1)
b110100100110 +
b100100 ,
#1100000
0#
0)
#1105000
b100111111011001 !
b10010111001101000001 "
1#
b10010111001101000001 (
1)
b100111111011001 +
b100100 ,
#1110000
0#
0)
#1115000
b110111110110 !
b11000100110100111100 "
1#
b11000100110100111100 (
1)
b110111110110 +
b100100 ,
#1120000
0#
0)
#1125000
b101010100000111 !
b10110111010011 "
1#
b10110111010011 (
1)
b101010100000111 +
b100100 ,
#1130000
0#
0)
#1135000
b111000000100001 !
b11110010001110101 "
1#
b11110010001110101 (
1)
b111000000100001 +
b100100 ,
#1140000
0#
0)
#1145000
b11111110101100 !
b11001111110001111 "
1#
b11001111110001111 (
1)
b11111110101100 +
b100100 ,
#1150000
0#
0)
#1155000
b1110111111101 !
b11000101010010111 "
1#
b11000101010010111 (
1)
b1110111111101 +
b100100 ,
#1160000
0#
0)
#1165000
b10000011110011 !
b100001001000011001 "
1#
b100001001000011001 (
1)
b10000011110011 +
b100100 ,
#1170000
0#
0)
#1175000
b101101101000100 !
b11001100110001100 "
1#
b11001100110001100 (
1)
b101101101000100 +
b100100 ,
#1180000
0#
0)
#1185000
b11001100111011 !
b11111110010101010110 "
1#
b11111110010101010110 (
1)
b11001100111011 +
b100100 ,
#1190000
0#
0)
#1195000
b11101111000100 !
b11110001111101011001 "
1#
b11110001111101011001 (
1)
b11101111000100 +
b100100 ,
#1200000
0#
0)
#1205000
b101001111111 !
b1011100010010010 "
1#
b1011100010010010 (
1)
b101001111111 +
b100100 ,
#1210000
0#
0)
#1215000
b110011010010011 !
b101011101010110010 "
1#
b101011101010110010 (
1)
b110011010010011 +
b100100 ,
#1220000
0#
0)
#1225000
b11110111101001 !
b11111101101010010 "
1#
b11111101101010010 (
1)
b11110111101001 +
b100100 ,
#1230000
0#
0)
#1235000
b110000100000 !
b11101000100101100110 "
1#
b11101000100101100110 (
1)
b110000100000 +
b100100 ,
#1240000
0#
0)
#1245000
b110111001001000 !
b11000001101001100100 "
1#
b11000001101001100100 (
1)
b110111001001000 +
b100100 ,
#1250000
0#
0)
#1255000
b11100011100101 !
b11010101111001111111 "
1#
b11010101111001111111 (
1)
b11100011100101 +
b100100 ,
#1260000
0#
0)
#1265000
b111010001101101 !
b100110111010101 "
1#
b100110111010101 (
1)
b111010001101101 +
b100100 ,
#1270000
0#
0)
#1275000
b101111101110010 !
b1011001010100011 "
1#
b1011001010100011 (
1)
b101111101110010 +
b100100 ,
#1280000
0#
0)
#1285000
b100101010011100 !
b11011011001011110000 "
1#
b11011011001011110000 (
1)
b100101010011100 +
b100100 ,
#1290000
0#
0)
#1295000
b100111111011101 !
b10110000110001001010 "
1#
b10110000110001001010 (
1)
b100111111011101 +
b100100 ,
#1300000
0#
0)
#1305000
b11100011110011 !
b11001001000010001111 "
1#
b11001001000010001111 (
1)
b11100011110011 +
b100100 ,
#1310000
0#
0)
#1315000
b101111010111100 !
b10110010100011000 "
1#
b10110010100011000 (
1)
b101111010111100 +
b100100 ,
#1320000
0#
0)
#1325000
b1011011100111 !
b1010010011101110101 "
1#
b1010010011101110101 (
1)
b1011011100111 +
b100100 ,
#1330000
0#
0)
#1335000
b111100001010001 !
b1001110001001110111 "
1#
b1001110001001110111 (
1)
b111100001010001 +
b100100 ,
#1340000
0#
0)
#1345000
b10010100110101 !
b100110010000000110 "
1#
b100110010000000110 (
1)
b10010100110101 +
b100100 ,
#1350000
0#
0)
#1355000
b1110100101001 !
b10111010110000011 "
1#
b10111010110000011 (
1)
b1110100101001 +
b100100 ,
#1360000
0#
0)
#1365000
b100011100100000 !
b110100010100011000 "
1#
b110100010100011000 (
1)
b100011100100000 +
b100100 ,
#1370000
0#
0)
#1375000
b10001110101000 !
b1010011011000110011 "
1#
b1010011011000110011 (
1)
b10001110101000 +
b100100 ,
#1380000
0#
0)
#1385000
b101001110011 !
b1000111101010011000 "
1#
b1000111101010011000 (
1)
b101001110011 +
b100100 ,
#1390000
0#
0)
#1395000
b100101011011101 !
b11100111110000011 "
1#
b11100111110000011 (
1)
b100101011011101 +
b100100 ,
#1400000
0#
0)
#1405000
b101111011011111 !
b1001001010110010 "
1#
b1001001010110010 (
1)
b101111011011111 +
b100100 ,
#1410000
0#
0)
#1415000
b10110100011011 !
b100011010101010001 "
1#
b100011010101010001 (
1)
b10110100011011 +
b100100 ,
#1420000
0#
0)
#1425000
b100000100 !
b1000011010000011011 "
1#
b1000011010000011011 (
1)
b100000100 +
b100100 ,
#1430000
0#
0)
#1435000
b110101010110001 !
b110010011010001011 "
1#
b110010011010001011 (
1)
b110101010110001 +
b100100 ,
#1440000
0#
0)
#1445000
b11011011110010 !
b11101101010100001000 "
1#
b11101101010100001000 (
1)
b11011011110010 +
b100100 ,
#1450000
0#
0)
#1455000
b101011011010100 !
b10101001111110000011 "
1#
b10101001111110000011 (
1)
b101011011010100 +
b100100 ,
#1460000
0#
0)
#1465000
b111111101100011 !
b10011101100111010110 "
1#
b10011101100111010110 (
1)
b111111101100011 +
b100100 ,
#1470000
0#
0)
#1475000
b1000100000 !
b11000111100011011110 "
1#
b11000111100011011110 (
1)
b1000100000 +
b100100 ,
#1480000
0#
0)
#1485000
b10100111100111 !
b11111011110011001001 "
1#
b11111011110011001001 (
1)
b10100111100111 +
b100100 ,
#1490000
0#
0)
#1495000
b110000010101101 !
b10111000100000001 "
1#
b10111000100000001 (
1)
b110000010101101 +
b100100 ,
#1500000
0#
0)
#1505000
b101110000011 !
b11010000101000110 "
1#
b11010000101000110 (
1)
b101110000011 +
b100100 ,
#1510000
0#
0)
#1515000
b1011110111011 !
b10111001101011111 "
1#
b10111001101011111 (
1)
b1011110111011 +
b100100 ,
#1520000
0#
0)
#1525000
b10110010101101 !
b11000101011011001 "
1#
b11000101011011001 (
1)
b10110010101101 +
b100100 ,
#1530000
0#
0)
#1535000
b10011001001000 !
b11001010111001111 "
1#
b11001010111001111 (
1)
b10011001001000 +
b100100 ,
#1540000
0#
0)
#1545000
b10011000011011 !
b10000111110010001 "
1#
b10000111110010001 (
1)
b10011000011011 +
b100100 ,
#1550000
0#
0)
#1555000
b10010010001001 !
b11111011100110010001 "
1#
b11111011100110010001 (
1)
b10010010001001 +
b100100 ,
#1560000
0#
0)
#1565000
b110010100100001 !
b11011111011001100111 "
1#
b11011111011001100111 (
1)
b110010100100001 +
b100100 ,
#1570000
0#
0)
#1575000
b11001001000100 !
b11001110010101000000 "
1#
b11001110010101000000 (
1)
b11001001000100 +
b100100 ,
#1580000
0#
0)
#1585000
b11100101001001 !
b11011010011010001010 "
1#
b11011010011010001010 (
1)
b11100101001001 +
b100100 ,
#1590000
0#
0)
#1595000
b11101001010 !
b1001101000011 "
1#
b1001101000011 (
1)
b11101001010 +
b100100 ,
#1600000
0#
0)
#1605000
b110010110010010 !
b100100001111011111 "
1#
b100100001111011111 (
1)
b110010110010010 +
b100100 ,
#1610000
0#
0)
#1615000
b110111001101100 !
b100010010000100001 "
1#
b100010010000100001 (
1)
b110111001101100 +
b100100 ,
#1620000
0#
0)
#1625000
b111001111100000 !
b11111111101110111001 "
1#
b11111111101110111001 (
1)
b111001111100000 +
b100100 ,
#1630000
0#
0)
#1635000
b11011101000101 !
b11100111111100001101 "
1#
b11100111111100001101 (
1)
b11011101000101 +
b100100 ,
#1640000
0#
0)
#1645000
b100010110001111 !
b11110111010110011001 "
1#
b11110111010110011001 (
1)
b100010110001111 +
b100100 ,
#1650000
0#
0)
#1655000
b111011001011000 !
b10111100101111001 "
1#
b10111100101111001 (
1)
b111011001011000 +
b100100 ,
#1660000
0#
0)
#1665000
b110100001111100 !
b11100010001100100 "
1#
b11100010001100100 (
1)
b110100001111100 +
b100100 ,
#1670000
0#
0)
#1675000
b111111011111011 !
b10111100111100 "
1#
b10111100111100 (
1)
b111111011111011 +
b100100 ,
#1680000
0#
0)
#1685000
b100011110111110 !
b11111100110010011001 "
1#
b11111100110010011001 (
1)
b100011110111110 +
b100100 ,
#1690000
0#
0)
#1695000
b11000101001010 !
b101010111100101010 "
1#
b101010111100101010 (
1)
b11000101001010 +
b100100 ,
#1700000
0#
0)
#1705000
b110100000101111 !
b1101001011110111111 "
1#
b1101001011110111111 (
1)
b110100000101111 +
b100100 ,
#1710000
0#
0)
#1715000
b110111010110 !
b1110110001101001111 "
1#
b1110110001101001111 (
1)
b110111010110 +
b100100 ,
#1720000
0#
0)
#1725000
b101101001000100 !
b1000101101100011001 "
1#
b1000101101100011001 (
1)
b101101001000100 +
b100100 ,
#1730000
0#
0)
#1735000
b11010010000111 !
b10111101000010100 "
1#
b10111101000010100 (
1)
b11010010000111 +
b100100 ,
#1740000
0#
0)
#1745000
b111000001010000 !
b100100010011111010 "
1#
b100100010011111010 (
1)
b111000001010000 +
b100100 ,
#1750000
0#
0)
#1755000
b110001000110110 !
b1010100011011010010 "
1#
b1010100011011010010 (
1)
b110001000110110 +
b100100 ,
#1760000
0#
0)
#1765000
b1001000110011 !
b1011100011111111101 "
1#
b1011100011111111101 (
1)
b1001000110011 +
b100100 ,
#1770000
0#
0)
#1775000
b100011000100101 !
b100000001011010000 "
1#
b100000001011010000 (
1)
b100011000100101 +
b100100 ,
#1780000
0#
0)
#1785000
b101111100011111 !
b11011010011011010101 "
1#
b11011010011011010101 (
1)
b101111100011111 +
b100100 ,
#1790000
0#
0)
#1795000
b10011000 !
b11010000110001101011 "
1#
b11010000110001101011 (
1)
b10011000 +
b100100 ,
#1800000
0#
0)
#1805000
b11101011110101 !
b11111011000010001111 "
1#
b11111011000010001111 (
1)
b11101011110101 +
b100100 ,
#1810000
0#
0)
#1815000
b111100001011 !
b10100010011100001 "
1#
b10100010011100001 (
1)
b111100001011 +
b100100 ,
#1820000
0#
0)
#1825000
b11111010100 !
b11110111111101011000 "
1#
b11110111111101011000 (
1)
b11111010100 +
b100100 ,
#1830000
0#
0)
#1835000
b10101001110011 !
b11000110110110011001 "
1#
b11000110110110011001 (
1)
b10101001110011 +
b100100 ,
#1840000
0#
0)
#1845000
b11101011011111 !
b10110110001000101011 "
1#
b10110110001000101011 (
1)
b11101011011111 +
b100100 ,
#1850000
0#
0)
#1855000
b111100010111 !
b11010000110100000101 "
1#
b11010000110100000101 (
1)
b111100010111 +
b100100 ,
#1860000
0#
0)
#1865000
b11011110001110 !
b11110110101100011010 "
1#
b11110110101100011010 (
1)
b11011110001110 +
b100100 ,
#1870000
0#
0)
#1875000
b11100010101 !
b110011100000011 "
1#
b110011100000011 (
1)
b11100010101 +
b100100 ,
#1880000
0#
0)
#1885000
b11001101100010 !
b11111110011011110000 "
1#
b11111110011011110000 (
1)
b11001101100010 +
b100100 ,
#1890000
0#
0)
#1895000
b111100111010011 !
b11110100001101010000 "
1#
b11110100001101010000 (
1)
b111100111010011 +
b100100 ,
#1900000
0#
0)
#1905000
b1000010111011 !
b11111010111110010110 "
1#
b11111010111110010110 (
1)
b1000010111011 +
b100100 ,
#1910000
0#
0)
#1915000
b1100100101011 !
b1101110011111010 "
1#
b1101110011111010 (
1)
b1100100101011 +
b100100 ,
#1920000
0#
0)
#1925000
b1001000011011 !
b10001110011100111 "
1#
b10001110011100111 (
1)
b1001000011011 +
b100100 ,
#1930000
0#
0)
#1935000
b110100001000110 !
b11110010100001001000 "
1#
b11110010100001001000 (
1)
b110100001000110 +
b100100 ,
#1940000
0#
0)
#1945000
b100111101011111 !
b10111111111001111100 "
1#
b10111111111001111100 (
1)
b100111101011111 +
b100100 ,
#1950000
0#
0)
#1955000
b110011000011 !
b10101000110001000101 "
1#
b10101000110001000101 (
1)
b110011000011 +
b100100 ,
#1960000
0#
0)
#1965000
b11101110011 !
b11001010001010110011 "
1#
b11001010001010110011 (
1)
b11101110011 +
b100100 ,
#1970000
0#
0)
#1975000
b110001001110001 !
b1101001011001001 "
1#
b1101001011001001 (
1)
b110001001110001 +
b100100 ,
#1980000
0#
0)
#1985000
b111100010000111 !
b111111000010010111 "
1#
b111111000010010111 (
1)
b111100010000111 +
b100100 ,
#1990000
0#
0)
#1995000
b11111001110001 !
b1000111010110000101 "
1#
b1000111010110000101 (
1)
b11111001110001 +
b100100 ,
#2000000
0#
0)
#2005000
b1001100100 !
b111011110011100010 "
1#
b111011110011100010 (
1)
b1001100100 +
b100100 ,
#2010000
0#
0)
#2015000
b100101010101011 !
b1000000100000001100 "
1#
b1000000100000001100 (
1)
b100101010101011 +
b100100 ,
